vlogger/__init__.py
vlogger/hoot.py
vlogger/nt4.py
vlogger/pds.py
vlogger/types.py
vlogger/wpilog.py
frc_vlogger-2026.0.5.dist-info/METADATA
frc_vlogger-2026.0.5.dist-info/WHEEL
frc_vlogger-2026.0.5.dist-info/licenses/LICENSE
frc_vlogger-2026.0.5.dist-info/RECORD
