Metadata-Version: 2.4
Name: frc-vlogger
Version: 2026.0.5
Summary: FRC post match + live match logging reader abstraction
License-Expression: Apache-2.0
License-File: LICENSE
Keywords: frc,parser,networktables,networktables,wpilog,hoot,ctre
Author: Ishan Karmakar
Author-email: ishan.karmakar24@gmail.com
Requires-Python: >=3.9
Classifier: Development Status :: 3 - Alpha
Classifier: Operating System :: OS Independent
Classifier: Programming Language :: Python
Classifier: Programming Language :: Python :: 3
Classifier: Programming Language :: Python :: 3.10
Classifier: Programming Language :: Python :: 3.11
Classifier: Programming Language :: Python :: 3.12
Classifier: Programming Language :: Python :: 3.13
Classifier: Programming Language :: Python :: 3.14
Classifier: Programming Language :: Python :: 3.15
Classifier: Intended Audience :: Developers
Requires-Dist: protobuf (>=6.0.0,<7.0.0)
Requires-Dist: pyntcore (>=2026.0.0,<2027.0.0)
Requires-Dist: robotpy-wpiutil (>=2026.0.0,<2027.0.0)
Project-URL: Changelog, https://git.valor6800.com/valor6800/vlogger/-/blob/main/CHANGELOG
Project-URL: Issues, https://git.valor6800.com/valor6800/vlogger/-/issues
Project-URL: Repository, https://git.valor6800.com/valor6800/vlogger
